santitools/__init__.py
santitools/colors.py
santitools/filesystem.py
santitools/math.py
santitools/time.py
santitools-1.1.dist-info/METADATA
santitools-1.1.dist-info/WHEEL
santitools-1.1.dist-info/licenses/LICENSE
santitools-1.1.dist-info/RECORD
