Metadata-Version: 2.1
Name: santitools
Version: 1.1
Summary: Santi's Tools: useful APIs for every Python dev!
Project-URL: Homepage, https://github.com/santi100a/santitools-python
Project-URL: Bug Tracker, https://github.com/santi100a/santitools-python/issues
Author-email: Santiago Rojas <santyrojasprieto9+pypi@gmail.com>
License-File: LICENSE
Classifier: Operating System :: OS Independent
Classifier: Programming Language :: Python :: 3
Requires-Python: >=3.7
